MANIFEST.in
README.md
requirements.txt
setup.py
test_requirements.txt
version.txt
cloudshell/__init__.py
cloudshell/tg/__init__.py
cloudshell/tg/breaking_point/__init__.py
cloudshell/tg/breaking_point/bp_exception.py
cloudshell/tg/breaking_point/actions/__init__.py
cloudshell/tg/breaking_point/actions/autoload_actions.py
cloudshell/tg/breaking_point/actions/port_reservation_actions.py
cloudshell/tg/breaking_point/actions/test_configuration_actions.py
cloudshell/tg/breaking_point/actions/test_execution_actions.py
cloudshell/tg/breaking_point/actions/test_network_actions.py
cloudshell/tg/breaking_point/actions/test_results_actions.py
cloudshell/tg/breaking_point/actions/test_statistics_actions.py
cloudshell/tg/breaking_point/autoload/__init__.py
cloudshell/tg/breaking_point/autoload/bp_autoload.py
cloudshell/tg/breaking_point/entities/__init__.py
cloudshell/tg/breaking_point/entities/bp_session.py
cloudshell/tg/breaking_point/flows/__init__.py
cloudshell/tg/breaking_point/flows/bp_autoload_flow.py
cloudshell/tg/breaking_point/flows/bp_download_test_file_flow.py
cloudshell/tg/breaking_point/flows/bp_flow.py
cloudshell/tg/breaking_point/flows/bp_load_configuration_file_flow.py
cloudshell/tg/breaking_point/flows/bp_load_pcap_file_flow.py
cloudshell/tg/breaking_point/flows/bp_port_reservation_flow.py
cloudshell/tg/breaking_point/flows/bp_results_flow.py
cloudshell/tg/breaking_point/flows/bp_statistics_flow.py
cloudshell/tg/breaking_point/flows/bp_test_execution_flow.py
cloudshell/tg/breaking_point/flows/exceptions.py
cloudshell/tg/breaking_point/helpers/__init__.py
cloudshell/tg/breaking_point/helpers/bp_cs_reservation_details.py
cloudshell/tg/breaking_point/helpers/port_reservation_helper.py
cloudshell/tg/breaking_point/helpers/quali_rest_api_helper.py
cloudshell/tg/breaking_point/rest_actions/__init__.py
cloudshell/tg/breaking_point/rest_actions/auth_actions.py
cloudshell/tg/breaking_point/rest_actions/exceptions.py
cloudshell_tg_breaking_point.egg-info/PKG-INFO
cloudshell_tg_breaking_point.egg-info/SOURCES.txt
cloudshell_tg_breaking_point.egg-info/dependency_links.txt
cloudshell_tg_breaking_point.egg-info/requires.txt
cloudshell_tg_breaking_point.egg-info/top_level.txt
