Metadata-Version: 1.0
Name: cloudshell-tg-breaking-point
Version: 2.0.2
Summary: QualiSystems Breaking Point Package
Home-page: http://www.qualisystems.com/
Author: Quali
Author-email: info@quali.com
License: UNKNOWN
Platform: UNKNOWN
